functime/__init__.py
functime/__main__.py
functime/config.py
functime/cross_validation.py
functime/log.py
functime/offsets.py
functime/preprocessing.py
functime/ranges.py
functime/stats.py
functime_client-0.1.4.dist-info/LICENSE
functime_client-0.1.4.dist-info/METADATA
functime_client-0.1.4.dist-info/WHEEL
functime_client-0.1.4.dist-info/entry_points.txt
functime_client-0.1.4.dist-info/top_level.txt
functime_client-0.1.4.dist-info/RECORD
