Metadata-Version: 2.1
Name: functime-client
Version: 0.1.4
Summary: The easiest way to run and deploy time-series ML (forecasting and classification) in the Cloud.
Author-email: Chris Lo <chris@functime.ai>, Daryl Lim <daryl@functime.ai>
Project-URL: Homepage, https://docs.functime.ai
Classifier: Development Status :: 4 - Beta
Classifier: Intended Audience :: Science/Research
Classifier: Intended Audience :: Developers
Classifier: Topic :: Software Development :: Libraries :: Python Modules
Classifier: Topic :: Scientific/Engineering
Classifier: Programming Language :: Python :: 3
Classifier: Programming Language :: Python :: 3.8
Classifier: Programming Language :: Python :: 3.9
Classifier: Programming Language :: Python :: 3.10
Classifier: Programming Language :: Python :: 3.11
Requires-Python: >=3.8
License-File: LICENSE
Requires-Dist: holidays
Requires-Dist: httpx[http2]
Requires-Dist: numpy
Requires-Dist: pandas
Requires-Dist: polars
Requires-Dist: pyarrow
Requires-Dist: rich (>=12.0.0)
Requires-Dist: scipy
Requires-Dist: toml
Requires-Dist: typer (>=0.6.1)
Provides-Extra: doc
Requires-Dist: mkdocs ; extra == 'doc'
Requires-Dist: mkdocs-material ; extra == 'doc'
Requires-Dist: mkdocstrings-python ; extra == 'doc'
Provides-Extra: test
Requires-Dist: coverage[toml] ; extra == 'test'
Requires-Dist: pytest-benchmark ; extra == 'test'
Requires-Dist: pytest-memray ; extra == 'test'
Requires-Dist: pytest-timeout ; extra == 'test'
Requires-Dist: pytest ; extra == 'test'
